setup.py
funniest_alef_bet_gimel_dalet/__init__.py
funniest_alef_bet_gimel_dalet.egg-info/PKG-INFO
funniest_alef_bet_gimel_dalet.egg-info/SOURCES.txt
funniest_alef_bet_gimel_dalet.egg-info/dependency_links.txt
funniest_alef_bet_gimel_dalet.egg-info/not-zip-safe
funniest_alef_bet_gimel_dalet.egg-info/requires.txt
funniest_alef_bet_gimel_dalet.egg-info/top_level.txt