Metadata-Version: 1.0
Name: funniest-alef-bet-gimel-dalet
Version: 0.6
Summary: The funniest joke in the world
Home-page: http://github.com/storborg/funniest
Author: Caesar Divi Filius Mortos Augustus
Author-email: flyingcircus@example.com
License: MIT
Platform: UNKNOWN
